{
	"info": {
		"_postman_id": "a78037c1-71a3-479c-b253-7cdc93c5430b",
		"name": "New Collection",
		"schema": "https://schema.getpostman.com/json/collection/v2.1.0/collection.json",
		"_exporter_id": "39282429"
	},
	"item": [
		{
			"name": "SmokeTest",
			"item": [
				{
					"name": "CreateBooking",
					"event": [
						{
							"listen": "test",
							"script": {
								"exec": [
									"var id = pm.response.json().bookingid;\r",
									"pm.globals.set(\"variable_key\", id);\r",
									"\r",
									"pm.test(\"Status code is 200\", function () {\r",
									"    pm.response.to.have.status(200);\r",
									"});"
								],
								"type": "text/javascript",
								"packages": {}
							}
						}
					],
					"request": {
						"method": "POST",
						"header": [],
						"body": {
							"mode": "raw",
							"raw": "{\r\n    \"firstname\" : \"Jim\",\r\n    \"lastname\" : \"Brown\",\r\n    \"totalprice\" : 111,\r\n    \"depositpaid\" : true,\r\n    \"bookingdates\" : {\r\n        \"checkin\" : \"2018-01-01\",\r\n        \"checkout\" : \"2019-01-01\"\r\n    },\r\n    \"additionalneeds\" : \"Breakfast\"\r\n}",
							"options": {
								"raw": {
									"language": "json"
								}
							}
						},
						"url": {
							"raw": "{{base_url}}/booking",
							"host": [
								"{{base_url}}"
							],
							"path": [
								"booking"
							]
						}
					},
					"response": []
				},
				{
					"name": "GetToken",
					"event": [
						{
							"listen": "test",
							"script": {
								"exec": [
									"const token_val = pm.response.json().token;\r",
									"console.log(token_val);\r",
									"pm.environment.set(\"token_key\", \"token=\"+token_val);"
								],
								"type": "text/javascript",
								"packages": {}
							}
						}
					],
					"request": {
						"method": "POST",
						"header": [],
						"body": {
							"mode": "raw",
							"raw": "{\r\n    \"username\" : {{user}},\r\n    \"password\" : {{pass}}\r\n}",
							"options": {
								"raw": {
									"language": "json"
								}
							}
						},
						"url": {
							"raw": "{{base_url}}/auth",
							"host": [
								"{{base_url}}"
							],
							"path": [
								"auth"
							]
						}
					},
					"response": []
				},
				{
					"name": "GetBookingIdList",
					"request": {
						"method": "GET",
						"header": [],
						"url": {
							"raw": "{{base_url}}/booking",
							"host": [
								"{{base_url}}"
							],
							"path": [
								"booking"
							]
						}
					},
					"response": []
				}
			]
		},
		{
			"name": "PositiveTest",
			"item": [
				{
					"name": "GetBooking",
					"event": [
						{
							"listen": "test",
							"script": {
								"exec": [
									"pm.test(\"Status code is 200\", function () {\r",
									"    pm.response.to.have.status(200);\r",
									"});"
								],
								"type": "text/javascript",
								"packages": {}
							}
						}
					],
					"request": {
						"method": "GET",
						"header": [],
						"url": {
							"raw": "{{base_url}}/booking/{{variable_key}}",
							"host": [
								"{{base_url}}"
							],
							"path": [
								"booking",
								"{{variable_key}}"
							]
						}
					},
					"response": []
				},
				{
					"name": "UpdateBooking",
					"event": [
						{
							"listen": "test",
							"script": {
								"exec": [
									""
								],
								"type": "text/javascript",
								"packages": {}
							}
						}
					],
					"request": {
						"method": "PUT",
						"header": [
							{
								"key": "Cookie",
								"value": "token=b6befec128ec4c2",
								"type": "text"
							},
							{
								"key": "Accept",
								"value": "application/json",
								"type": "text",
								"disabled": true
							}
						],
						"body": {
							"mode": "raw",
							"raw": "{\r\n    \"firstname\" : \"James\",\r\n    \"lastname\" : \"Green\",\r\n    \"totalprice\" : 111,\r\n    \"depositpaid\" : true,\r\n    \"bookingdates\" : {\r\n        \"checkin\" : \"2018-01-01\",\r\n        \"checkout\" : \"2019-01-01\"\r\n    },\r\n    \"additionalneeds\" : \"Breakfast\"\r\n}",
							"options": {
								"raw": {
									"language": "json"
								}
							}
						},
						"url": {
							"raw": "{{base_url}}/booking/{{variable_key}}",
							"host": [
								"{{base_url}}"
							],
							"path": [
								"booking",
								"{{variable_key}}"
							]
						}
					},
					"response": []
				},
				{
					"name": "DeleteBooking",
					"event": [
						{
							"listen": "test",
							"script": {
								"exec": [
									"pm.test(\"Status code is 201\", function () {\r",
									"    pm.response.to.have.status(201);\r",
									"});"
								],
								"type": "text/javascript",
								"packages": {}
							}
						}
					],
					"request": {
						"method": "DELETE",
						"header": [
							{
								"key": "Cookie",
								"value": "{{token_key}}",
								"type": "text"
							}
						],
						"url": {
							"raw": "{{base_url}}/booking/{{variable_key}}",
							"host": [
								"{{base_url}}"
							],
							"path": [
								"booking",
								"{{variable_key}}"
							]
						}
					},
					"response": []
				}
			]
		}
	],
	"event": [
		{
			"listen": "prerequest",
			"script": {
				"type": "text/javascript",
				"packages": {},
				"exec": [
					""
				]
			}
		},
		{
			"listen": "test",
			"script": {
				"type": "text/javascript",
				"packages": {},
				"exec": [
					""
				]
			}
		}
	],
	"variable": [
		{
			"key": "base_url",
			"value": "https://restful-booker.herokuapp.com",
			"type": "string",
			"disabled": true
		}
	]
}